ecs_rollback.py
app/__init__.py
app/app.py
ecs_rollback-1.0.0.dist-info/LICENSE
ecs_rollback-1.0.0.dist-info/METADATA
ecs_rollback-1.0.0.dist-info/WHEEL
ecs_rollback-1.0.0.dist-info/entry_points.txt
ecs_rollback-1.0.0.dist-info/top_level.txt
ecs_rollback-1.0.0.dist-info/RECORD
